[{"Id":0,"Name":"Murad","Surname":"Seyidov","Email":"smurad@e.com","Phone":"0557777777","ImgUrl":null},{"Id":1,"Name":"Susan","Surname":"Mercer","Email":"santino2015@yahoo.com","Phone":"313-608-5624","ImgUrl":"https://i0.wp.com/newdoorfiji.com/wp-content/uploads/2018/03/profile-img-1.jpg?ssl=1"},{"Id":2,"Name":"Phillip","Surname":"Clever","Email":"felton1973@yahoo.com","Phone":"215-840-8115","ImgUrl":"https://bdebopam.github.io/static/media/profile-picture.8457ea82.png"},{"Id":3,"Name":"Eric","Surname":"Williams","Email":"margarita_dani@hotmail.com","Phone":"330-281-8254","ImgUrl":"https://www.fakepersongenerator.com/Face/male/male20151085943767761.jpg"}]